pm_mcp_servers/__init__.py
pm_mcp_servers/shared.py
pm_mcp_servers/pm_analyse/__init__.py
pm_mcp_servers/pm_analyse/analyzers.py
pm_mcp_servers/pm_analyse/forecasters.py
pm_mcp_servers/pm_analyse/models.py
pm_mcp_servers/pm_analyse/risk_engine.py
pm_mcp_servers/pm_analyse/server.py
pm_mcp_servers/pm_analyse/tools.py
pm_mcp_servers/pm_data/__init__.py
pm_mcp_servers/pm_data/server.py
pm_mcp_servers/pm_data/tools.py
pm_mcp_servers/pm_validate/__init__.py
pm_mcp_servers/pm_validate/server.py
pm_mcp_servers/pm_validate/tools.py
pm_mcp_servers-0.3.0.dist-info/licenses/LICENSE
pm_mcp_servers-0.3.0.dist-info/METADATA
pm_mcp_servers-0.3.0.dist-info/WHEEL
pm_mcp_servers-0.3.0.dist-info/entry_points.txt
pm_mcp_servers-0.3.0.dist-info/top_level.txt
pm_mcp_servers-0.3.0.dist-info/RECORD
