Metadata-Version: 2.4
Name: pm-mcp-servers
Version: 0.3.0
Summary: MCP servers for AI-enabled project management. Enables Claude to interact with PM data.
Author: Members of the PDA Task Force
License: MIT
Project-URL: Homepage, https://github.com/PDA-Task-Force/pda-platform
Project-URL: Repository, https://github.com/PDA-Task-Force/pda-platform
Project-URL: Documentation, https://github.com/PDA-Task-Force/pda-platform/tree/main/packages/pm-mcp-servers
Project-URL: Issues, https://github.com/PDA-Task-Force/pda-platform/issues
Keywords: mcp,model-context-protocol,claude,ai,project-management
Requires-Python: >=3.10
License-File: LICENSE
Requires-Dist: mcp>=0.9.0
Requires-Dist: pm-data-tools>=0.2.0
Provides-Extra: dev
Requires-Dist: pytest>=7.0; extra == "dev"
Requires-Dist: pytest-asyncio>=0.21; extra == "dev"
Requires-Dist: pytest-cov>=4.0; extra == "dev"
Requires-Dist: mypy>=1.0; extra == "dev"
Dynamic: license-file
